README.md
setup.cfg
setup.py
yd3/__init__.py
yd3/yd3.py
yd3.egg-info/PKG-INFO
yd3.egg-info/SOURCES.txt
yd3.egg-info/dependency_links.txt
yd3.egg-info/entry_points.txt
yd3.egg-info/requires.txt
yd3.egg-info/top_level.txt