Metadata-Version: 1.0
Name: yd3
Version: 0.1.2
Summary: bilingual dictionary in command line
Home-page: https://github.com/Tacsy/yd3
Author: Xuyan Ru
Author-email: lelielru@gmail.com
License: MIT
Keywords: dictionary,chinese,command line
Platform: UNKNOWN
